{
  "backtest_info": {
    "ticker": "BUOU.SI",
    "start_date": "2025-01-01",
    "end_date": "2026-06-26",
    "duration_days": 541,
    "initial_capital": 10000,
    "final_equity": 10082.034026622681,
    "total_return": 82.03402662268127,
    "total_return_percent": 0.8203402662268126,
    "num_trades": 32,
    "num_winning": 16,
    "num_losing": 16,
    "strategy_name": "Technical Analysis Strategy"
  },
  "performance_metrics": {
    "total_return": 82.03402662268127,
    "total_return_percent": 0.8203402662268126,
    "annualized_return": 0.005527284523109133,
    "cumulative_return": 0.008203402662268156,
    "volatility": 0.001006387477090729,
    "annualized_volatility": 0.015975905921710692,
    "sharpe_ratio": -0.9059089073141673,
    "sortino_ratio": -1.0414123110115932,
    "calmar_ratio": 0.2101996547083855,
    "max_drawdown": -265.3429192992953,
    "max_drawdown_percent": -2.6295402486637065,
    "avg_drawdown": -121.38969178952605,
    "max_drawdown_duration_days": 327,
    "num_trades": 32,
    "num_winning_trades": 16,
    "num_losing_trades": 16,
    "win_rate": 50.0,
    "profit_factor": 1.1543604195607473,
    "avg_win": 61.79401200023389,
    "avg_loss": 53.53095181810505,
    "avg_win_percent": 6.2339087461141425,
    "avg_loss_percent": 5.379878092175696,
    "largest_win": 71.88970981455077,
    "largest_loss": 74.16564517798906,
    "expectancy": 4.13153009106442,
    "avg_trade_duration_days": 33.0625,
    "alpha": 0.0,
    "beta": 0.0,
    "r_squared": 0.0,
    "value_at_risk_95": -0.0015625171492516631,
    "conditional_var_95": -0.002418410837821764
  }
}