{
  "backtest_info": {
    "ticker": "META",
    "start_date": "2025-01-01",
    "end_date": "2026-01-27",
    "duration_days": 391,
    "initial_capital": 10000,
    "final_equity": 9956.459345582109,
    "total_return": -43.540654417891346,
    "total_return_percent": -0.43540654417891345,
    "num_trades": 22,
    "num_winning": 10,
    "num_losing": 12,
    "strategy_name": "Technical Analysis Strategy"
  },
  "performance_metrics": {
    "total_return": -43.540654417891346,
    "total_return_percent": -0.43540654417891345,
    "annualized_return": -0.004065126106225558,
    "cumulative_return": -0.004354065441789179,
    "volatility": 0.0013607693674247895,
    "annualized_volatility": 0.021601544027524025,
    "sharpe_ratio": -1.114046573502455,
    "sortino_ratio": -0.8740787267371665,
    "calmar_ratio": 0.16908785285245787,
    "max_drawdown": -242.2291433914961,
    "max_drawdown_percent": -2.404150290898006,
    "avg_drawdown": -97.93548605234369,
    "max_drawdown_duration_days": 145,
    "num_trades": 22,
    "num_winning_trades": 10,
    "num_losing_trades": 12,
    "win_rate": 45.45454545454545,
    "profit_factor": 0.8471768902519186,
    "avg_win": 61.53274208338935,
    "avg_loss": 60.527247213085786,
    "avg_win_percent": 6.202479456716582,
    "avg_loss_percent": 6.05846047478607,
    "largest_win": 69.66641323246802,
    "largest_loss": 94.0626712594152,
    "expectancy": -5.04543389650618,
    "avg_trade_duration_days": 15.363636363636363,
    "alpha": 0.0,
    "beta": 0.0,
    "r_squared": 0.0,
    "value_at_risk_95": -0.001677739720937571,
    "conditional_var_95": -0.003406338247797979
  }
}