{
  "backtest_info": {
    "ticker": "GOOGL",
    "start_date": "2025-01-01",
    "end_date": "2026-06-17",
    "duration_days": 532,
    "initial_capital": 10000,
    "final_equity": 10124.917125208935,
    "total_return": 124.91712520893452,
    "total_return_percent": 1.2491712520893452,
    "num_trades": 18,
    "num_winning": 8,
    "num_losing": 10,
    "strategy_name": "Technical Analysis Strategy"
  },
  "performance_metrics": {
    "total_return": 124.91712520893452,
    "total_return_percent": 1.2491712520893452,
    "annualized_return": 0.008553729623083761,
    "cumulative_return": 0.012491712520893428,
    "volatility": 0.0011924632676414383,
    "annualized_volatility": 0.018929767522552206,
    "sharpe_ratio": -0.6046704146408342,
    "sortino_ratio": -0.7059846338729051,
    "calmar_ratio": 0.5343906801373454,
    "max_drawdown": -163.96655036766606,
    "max_drawdown_percent": -1.6006509733450704,
    "avg_drawdown": -65.56047954327444,
    "max_drawdown_duration_days": 56,
    "num_trades": 18,
    "num_winning_trades": 8,
    "num_losing_trades": 10,
    "win_rate": 44.44444444444444,
    "profit_factor": 1.5149635807875523,
    "avg_win": 84.44640473051092,
    "avg_loss": 44.593232894278046,
    "avg_win_percent": 8.438615344741276,
    "avg_loss_percent": 4.426202960241414,
    "largest_win": 155.42268464699146,
    "largest_loss": 63.78754074876554,
    "expectancy": 12.757717161183715,
    "avg_trade_duration_days": 14.88888888888889,
    "alpha": 0.0,
    "beta": 0.0,
    "r_squared": 0.0,
    "value_at_risk_95": -0.001778961059358175,
    "conditional_var_95": -0.002582742380824984
  }
}