{
  "backtest_info": {
    "ticker": "M44U.SI",
    "start_date": "2025-01-01",
    "end_date": "2026-04-19",
    "duration_days": 473,
    "initial_capital": 10000,
    "final_equity": 10062.09361246819,
    "total_return": 62.09361246819026,
    "total_return_percent": 0.6209361246819026,
    "num_trades": 30,
    "num_winning": 14,
    "num_losing": 16,
    "strategy_name": "Technical Analysis Strategy"
  },
  "performance_metrics": {
    "total_return": 62.09361246819026,
    "total_return_percent": 0.6209361246819026,
    "annualized_return": 0.004788190872928588,
    "cumulative_return": 0.006209361246819034,
    "volatility": 0.0009788486593742057,
    "annualized_volatility": 0.01553874074323873,
    "sharpe_ratio": -0.9789602245401016,
    "sortino_ratio": -0.9464663923212904,
    "calmar_ratio": 0.2451253423309838,
    "max_drawdown": -197.94779228257357,
    "max_drawdown_percent": -1.9533642778000773,
    "avg_drawdown": -102.25802173977402,
    "max_drawdown_duration_days": 269,
    "num_trades": 30,
    "num_winning_trades": 14,
    "num_losing_trades": 16,
    "win_rate": 46.666666666666664,
    "profit_factor": 1.1109216321647386,
    "avg_win": 65.87157957434094,
    "avg_loss": 51.88271652901007,
    "avg_win_percent": 6.599493773158875,
    "avg_loss_percent": 5.166706358317024,
    "largest_win": 73.44228406148284,
    "largest_loss": 93.67064742789705,
    "expectancy": 3.069288319220406,
    "avg_trade_duration_days": 33.0,
    "alpha": 0.0,
    "beta": 0.0,
    "r_squared": 0.0,
    "value_at_risk_95": -0.0014797003989446334,
    "conditional_var_95": -0.002466818139180755
  }
}