{
  "backtest_info": {
    "ticker": "GOOGL",
    "start_date": "2025-01-01",
    "end_date": "2026-05-27",
    "duration_days": 511,
    "initial_capital": 10000,
    "final_equity": 10353.856481524257,
    "total_return": 353.8564815242571,
    "total_return_percent": 3.538564815242571,
    "num_trades": 18,
    "num_winning": 12,
    "num_losing": 6,
    "strategy_name": "Technical Analysis Strategy"
  },
  "performance_metrics": {
    "total_return": 353.8564815242571,
    "total_return_percent": 3.538564815242571,
    "annualized_return": 0.025149592533334486,
    "cumulative_return": 0.03538564815242573,
    "volatility": 0.001312581566254767,
    "annualized_volatility": 0.02083658639878658,
    "sharpe_ratio": 0.2471418511063968,
    "sortino_ratio": 0.3697391003221545,
    "calmar_ratio": 1.5712102733287634,
    "max_drawdown": -166.3116676676691,
    "max_drawdown_percent": -1.6006509733450636,
    "avg_drawdown": -57.85501912309932,
    "max_drawdown_duration_days": 56,
    "num_trades": 18,
    "num_winning_trades": 12,
    "num_losing_trades": 6,
    "win_rate": 66.66666666666666,
    "profit_factor": 3.2984289775439986,
    "avg_win": 82.15877292661021,
    "avg_loss": 49.81691192137502,
    "avg_win_percent": 8.122956429999114,
    "avg_loss_percent": 4.906383625121456,
    "largest_win": 157.64560405196391,
    "largest_loss": 57.63818922071266,
    "expectancy": 38.16687797728181,
    "avg_trade_duration_days": 16.88888888888889,
    "alpha": 0.0,
    "beta": 0.0,
    "r_squared": 0.0,
    "value_at_risk_95": -0.0012674753521997094,
    "conditional_var_95": -0.0022591266615158336
  }
}