{
  "backtest_info": {
    "ticker": "AMZN",
    "start_date": "2025-01-01",
    "end_date": "2026-06-09",
    "duration_days": 524,
    "initial_capital": 10000,
    "final_equity": 10074.300139675412,
    "total_return": 74.30013967541163,
    "total_return_percent": 0.7430013967541163,
    "num_trades": 24,
    "num_winning": 10,
    "num_losing": 14,
    "strategy_name": "Technical Analysis Strategy"
  },
  "performance_metrics": {
    "total_return": 74.30013967541163,
    "total_return_percent": 0.7430013967541163,
    "annualized_return": 0.005169671444239077,
    "cumulative_return": 0.007430013967541171,
    "volatility": 0.001289959190532102,
    "annualized_volatility": 0.020477467317420762,
    "sharpe_ratio": -0.7242266988332264,
    "sortino_ratio": -0.7832483214581462,
    "calmar_ratio": 0.3326859619928145,
    "max_drawdown": -157.85717284830753,
    "max_drawdown_percent": -1.5539193217749094,
    "avg_drawdown": -63.458340537522645,
    "max_drawdown_duration_days": 89,
    "num_trades": 24,
    "num_winning_trades": 10,
    "num_losing_trades": 14,
    "win_rate": 41.66666666666667,
    "profit_factor": 1.1694310137514432,
    "avg_win": 84.52620793630021,
    "avg_loss": 51.628409116636966,
    "avg_win_percent": 8.45778612560381,
    "avg_loss_percent": 5.129644778819403,
    "largest_win": 116.82565072530451,
    "largest_loss": 71.78608192308275,
    "expectancy": 5.102681322086862,
    "avg_trade_duration_days": 10.833333333333334,
    "alpha": 0.0,
    "beta": 0.0,
    "r_squared": 0.0,
    "value_at_risk_95": -0.00178137072604459,
    "conditional_var_95": -0.0030072452034648734
  }
}