{
  "backtest_info": {
    "ticker": "CRPU.SI",
    "start_date": "2025-01-01",
    "end_date": "2026-03-31",
    "duration_days": 454,
    "initial_capital": 10000,
    "final_equity": 10055.688479524568,
    "total_return": 55.68847952456781,
    "total_return_percent": 0.5568847952456781,
    "num_trades": 18,
    "num_winning": 8,
    "num_losing": 10,
    "strategy_name": "Technical Analysis Strategy"
  },
  "performance_metrics": {
    "total_return": 55.68847952456781,
    "total_return_percent": 0.5568847952456781,
    "annualized_return": 0.004474719068982225,
    "cumulative_return": 0.0055688479524567125,
    "volatility": 0.0008619629324645342,
    "annualized_volatility": 0.013683237351942722,
    "sharpe_ratio": -1.134620450679643,
    "sortino_ratio": -1.3993798480932136,
    "calmar_ratio": 0.3481678555611298,
    "max_drawdown": -129.921022305336,
    "max_drawdown_percent": -1.2852188958600095,
    "avg_drawdown": -56.606455289007826,
    "max_drawdown_duration_days": 237,
    "num_trades": 18,
    "num_winning_trades": 8,
    "num_losing_trades": 10,
    "win_rate": 44.44444444444444,
    "profit_factor": 1.2111993657484652,
    "avg_win": 65.40959969066256,
    "avg_loss": 43.20319282878254,
    "avg_win_percent": 6.532107615363927,
    "avg_loss_percent": 4.288855581905926,
    "largest_win": 74.18573915032937,
    "largest_loss": 65.02268892036125,
    "expectancy": 5.069159402081949,
    "avg_trade_duration_days": 61.44444444444444,
    "alpha": 0.0,
    "beta": 0.0,
    "r_squared": 0.0,
    "value_at_risk_95": -0.001450465187442851,
    "conditional_var_95": -0.0018729261784230882
  }
}