{
  "backtest_info": {
    "ticker": "AMZN",
    "start_date": "2025-01-01",
    "end_date": "2026-01-22",
    "duration_days": 386,
    "initial_capital": 10000,
    "final_equity": 9743.722066687265,
    "total_return": -256.2779333127346,
    "total_return_percent": -2.562779333127346,
    "num_trades": 24,
    "num_winning": 6,
    "num_losing": 18,
    "strategy_name": "Technical Analysis Strategy"
  },
  "performance_metrics": {
    "total_return": -256.2779333127346,
    "total_return_percent": -2.562779333127346,
    "annualized_return": -0.024250583251370528,
    "cumulative_return": -0.025627793331273407,
    "volatility": 0.0012561143415994415,
    "annualized_volatility": 0.019940196996802544,
    "sharpe_ratio": -2.219164798545682,
    "sortino_ratio": -1.8665492534381591,
    "calmar_ratio": 0.785907185669544,
    "max_drawdown": -309.79458446392164,
    "max_drawdown_percent": -3.0856803059652065,
    "avg_drawdown": -128.63061124950272,
    "max_drawdown_duration_days": 120,
    "num_trades": 24,
    "num_winning_trades": 6,
    "num_losing_trades": 18,
    "win_rate": 25.0,
    "profit_factor": 0.4137302154307048,
    "avg_win": 63.28073066476194,
    "avg_loss": 50.98389264679393,
    "avg_win_percent": 6.382312746020997,
    "avg_loss_percent": 5.129705718062758,
    "largest_win": 70.1790576544181,
    "largest_loss": 66.48975898084336,
    "expectancy": -22.417736818904967,
    "avg_trade_duration_days": 13.666666666666666,
    "alpha": 0.0,
    "beta": 0.0,
    "r_squared": 0.0,
    "value_at_risk_95": -0.0019354271437361569,
    "conditional_var_95": -0.0036873268034749015
  }
}