{
  "backtest_info": {
    "ticker": "M44U.SI",
    "start_date": "2025-01-01",
    "end_date": "2026-02-13",
    "duration_days": 408,
    "initial_capital": 10000,
    "final_equity": 10022.833662507941,
    "total_return": 22.83366250794097,
    "total_return_percent": 0.22833662507940972,
    "num_trades": 24,
    "num_winning": 10,
    "num_losing": 14,
    "strategy_name": "Technical Analysis Strategy"
  },
  "performance_metrics": {
    "total_return": 22.83366250794097,
    "total_return_percent": 0.22833662507940972,
    "annualized_return": 0.0020424717744222942,
    "cumulative_return": 0.002283366250794172,
    "volatility": 0.0009297963472260686,
    "annualized_volatility": 0.01476005942817863,
    "sharpe_ratio": -1.2166298051141138,
    "sortino_ratio": -1.0928017336159357,
    "calmar_ratio": 0.104125192272438,
    "max_drawdown": -197.94742511409459,
    "max_drawdown_percent": -1.9615539043407249,
    "avg_drawdown": -109.84284099745217,
    "max_drawdown_duration_days": 345,
    "num_trades": 24,
    "num_winning_trades": 10,
    "num_losing_trades": 14,
    "win_rate": 41.66666666666667,
    "profit_factor": 1.028749998826229,
    "avg_win": 70.32328305491892,
    "avg_loss": 48.827136354907516,
    "avg_win_percent": 7.0596147137438425,
    "avg_loss_percent": 4.870357788319086,
    "largest_win": 76.2201590075548,
    "largest_loss": 93.67065279972383,
    "expectancy": 0.8188717325201651,
    "avg_trade_duration_days": 31.083333333333332,
    "alpha": 0.0,
    "beta": 0.0,
    "r_squared": 0.0,
    "value_at_risk_95": -0.0008865690498199852,
    "conditional_var_95": -0.0022671245519422737
  }
}