{
  "report_date": "2025-12-08 13:51:11",
  "total_analyzed": 6,
  "summary": {
    "buy": 2,
    "sell": 0,
    "hold": 4
  },
  "signals": [
    {
      "ticker": "CRPU.SI",
      "name": "Sasseur Reit",
      "signal": "HOLD",
      "confidence": 49.59,
      "last_close": 0.68,
      "atr": 0.0084,
      "entry_zone": {
        "lower": 0.67,
        "upper": 0.68
      },
      "timeframe": "1d",
      "is_actionable": false,
      "analysis": [
        "RSI 43.2 - Neutral (trend: v)",
        "MACD Bearish Momentum (spread: -0.0004, d_hist: -0.0001)",
        "OBV slope 276166.7 - Bullish volume flow",
        "MA50 0.68 vs MA200 0.64 - Mild Bullish Trend (spread: 5.8%)",
        "BB Mild Bullish (lower half) - price lower<->middle (tight bands, width: 0.021)",
        "Volume 504,700 vs SMA20 1,103,620 - Weak Bearish (low volume) (ratio: 0.46x)",
        "Neutral Candlesticks 0.38 : bear_marubozu",
        "Weak trend (ADX=19.5) - reduced confidence",
        "Near S/R level at $0.67"
      ]
    },
    {
      "ticker": "J69U.SI",
      "name": "FRASERS CENTREPOINT TRUST",
      "signal": "BUY",
      "confidence": 65.35,
      "last_close": 2.26,
      "atr": 0.0296,
      "entry_zone": {
        "lower": 2.25,
        "upper": 2.28
      },
      "timeframe": "1d",
      "is_actionable": true,
      "analysis": [
        "RSI 45.0 - Neutral (trend: -)",
        "MACD Mild Bullish (spread: 0.0032, d_hist: -0.0009)",
        "OBV slope -1741900.0 - Strong Bearish volume flow",
        "MA50 2.30 vs MA200 2.19 - Mild Bullish Trend (spread: 4.8%)",
        "BB Mild Bullish (lower half) - price lower<->middle (normal bands, width: 0.041)",
        "Volume 1,166,600 vs SMA20 4,767,525 - Neutral (low volume) (ratio: 0.24x)",
        "Neutral Candlesticks 0.19 : bear_marubozu",
        "Near S/R level at $2.23"
      ]
    },
    {
      "ticker": "BUOU.SI",
      "name": "FRASERS LOGISTICS & COM TRUST",
      "signal": "HOLD",
      "confidence": 57.9,
      "last_close": 0.97,
      "atr": 0.0138,
      "entry_zone": {
        "lower": 0.96,
        "upper": 0.98
      },
      "timeframe": "1d",
      "is_actionable": false,
      "analysis": [
        "RSI 57.4 - Neutral (trend: v)",
        "MACD Mild Bullish (spread: 0.0015, d_hist: -0.0015)",
        "OBV slope -2034633.3 - Bearish volume flow",
        "MA50 0.94 vs MA200 0.86 - Strong Bullish Trend (spread: 9.6%)",
        "BB Mild Bearish (upper half) - price middle<->upper (wide bands, width: 0.089)",
        "Volume 9,353,400 vs SMA20 15,128,105 - Weak Bearish (low volume) (ratio: 0.62x)",
        "Neutral Candlesticks 0.21 : bull_marubozu",
        "Strong trend (ADX=74.7) - boosted confidence",
        "Near S/R level at $0.95"
      ]
    },
    {
      "ticker": "M44U.SI",
      "name": "Mapletree Log Tr",
      "signal": "HOLD",
      "confidence": 40.6,
      "last_close": 1.29,
      "atr": 0.0208,
      "entry_zone": {
        "lower": 1.28,
        "upper": 1.31
      },
      "timeframe": "1d",
      "is_actionable": false,
      "analysis": [
        "RSI 46.2 - Neutral (trend: -)",
        "MACD Bearish Momentum (spread: -0.0027, d_hist: -0.0006)",
        "OBV slope -3289233.3 - Bearish volume flow",
        "MA50 1.29 vs MA200 1.18 - Strong Bullish Trend (spread: 8.6%)",
        "BB Mild Bullish (lower half) - price lower<->middle (normal bands, width: 0.042)",
        "Volume 3,971,700 vs SMA20 10,493,355 - Neutral (low volume) (ratio: 0.38x)",
        "Neutral Candlesticks 0.05 : bull_marubozu",
        "Near S/R level at $1.26"
      ]
    },
    {
      "ticker": "ME8U.SI",
      "name": "Mapletree Ind Tr",
      "signal": "BUY",
      "confidence": 78.19,
      "last_close": 2.02,
      "atr": 0.0234,
      "entry_zone": {
        "lower": 2.01,
        "upper": 2.04
      },
      "timeframe": "1d",
      "is_actionable": true,
      "analysis": [
        "RSI 41.0 - Neutral (trend: v)",
        "MACD Mild Bullish (spread: 0.0013, d_hist: -0.0007)",
        "OBV slope -982600.0 - Strong Bearish volume flow",
        "MA50 2.08 vs MA200 1.99 - Mild Bullish Trend (spread: 4.7%)",
        "BB Mild Bullish (lower half) - price lower<->middle (tight bands, width: 0.023)",
        "Volume 3,507,400 vs SMA20 6,682,760 - Weak Bearish (low volume) (ratio: 0.52x)",
        "Neutral Candlesticks 0.26 : bull_marubozu",
        "Strong trend (ADX=43.6) - boosted confidence",
        "Near S/R level at $2.02"
      ]
    },
    {
      "ticker": "JYEU.SI",
      "name": "Lendlease Reit",
      "signal": "HOLD",
      "confidence": 50.0,
      "last_close": 0.61,
      "atr": 0.0132,
      "entry_zone": {
        "lower": 0.6,
        "upper": 0.62
      },
      "timeframe": "1d",
      "is_actionable": false,
      "analysis": [
        "RSI 44.7 - Neutral (trend: v)",
        "MACD Mild Bullish (spread: 0.0001, d_hist: -0.0007)",
        "OBV slope 5794333.3 - Bullish volume flow",
        "MA50 0.62 vs MA200 0.54 - Mild Bullish Trend (spread: 15.8%)",
        "BB Mild Bullish (lower half) - price lower<->middle (normal bands, width: 0.061)",
        "Volume 17,882,300 vs SMA20 21,154,190 - Mild Bearish (normal volume) (ratio: 0.85x)",
        "Neutral Candlesticks 0.40 : bull_rising_sun",
        "Near S/R level at $0.64"
      ]
    }
  ]
}