{
  "report_date": "2026-02-26 14:31:00",
  "total_analyzed": 11,
  "summary": {
    "buy": 7,
    "sell": 0,
    "hold": 4
  },
  "signals": [
    {
      "ticker": "AAPL",
      "name": "AAPL",
      "signal": "BUY",
      "confidence": 67.85,
      "last_close": 274.23,
      "atr": 6.4401,
      "entry_zone": {
        "lower": 271.01,
        "upper": 279.38
      },
      "timeframe": "1d",
      "is_actionable": true,
      "analysis": [
        "RSI 58.6 - Neutral (trend: ^)",
        "MACD Bullish Momentum (spread: 0.5475, d_hist: 0.4448)",
        "OBV slope 39345705.9 - Bullish volume flow",
        "MA50 265.68 vs MA200 242.28 - Strong Bullish Trend (spread: 9.7%)",
        "BB Mild Bearish (upper half) - price middle<->upper (wide bands, width: 0.109)",
        "Volume 33,714,343 vs SMA20 54,259,693 - Weak Bullish (low volume) (ratio: 0.62x)",
        "Neutral Candlesticks 0.14 : ",
        "Weak trend (ADX=18.1) - reduced confidence",
        "Near S/R level at $277.32"
      ]
    },
    {
      "ticker": "MSFT",
      "name": "MSFT",
      "signal": "BUY",
      "confidence": 75.68,
      "last_close": 400.6,
      "atr": 11.0744,
      "entry_zone": {
        "lower": 395.06,
        "upper": 409.46
      },
      "timeframe": "1d",
      "is_actionable": true,
      "analysis": [
        "RSI 39.6 - Bullish (trend: ^)",
        "MACD Strong Bullish Crossover (spread: 0.8087, d_hist: 1.0719)",
        "OBV slope 11423954.8 - Strong Bullish volume flow",
        "MA50 448.53 vs MA200 486.23 - Strong Bearish Trend (spread: -7.8%)",
        "BB Mild Bullish (lower half) - price lower<->middle (wide bands, width: 0.208)",
        "Volume 43,625,483 vs SMA20 46,939,082 - Mild Bullish (normal volume) (ratio: 0.93x)",
        "Neutral Candlesticks 0.31 : bull_harami",
        "Strong trend (ADX=60.4) - boosted confidence"
      ]
    },
    {
      "ticker": "GOOGL",
      "name": "GOOGL",
      "signal": "HOLD",
      "confidence": 56.13,
      "last_close": 310.16,
      "atr": 8.4442,
      "entry_zone": {
        "lower": 305.94,
        "upper": 316.92
      },
      "timeframe": "1d",
      "is_actionable": false,
      "analysis": [
        "RSI 42.6 - Neutral (trend: v)",
        "MACD Neutral Bearish (spread: -0.7165, d_hist: 0.2595)",
        "OBV slope 1270594.0 - Strong Bullish volume flow",
        "MA50 319.97 vs MA200 248.85 - Mild Bullish Trend (spread: 28.6%)",
        "BB Mild Bullish (lower half) - price lower<->middle (wide bands, width: 0.171)",
        "Volume 536,193 vs SMA20 39,965,890 - Weak Bearish (low volume) (ratio: 0.01x)",
        "Neutral Candlesticks 0.09 : bear_engulfing",
        "Strong trend (ADX=61.1) - boosted confidence",
        "Near S/R level at $296.12"
      ]
    },
    {
      "ticker": "NVDA",
      "name": "NVDA",
      "signal": "BUY",
      "confidence": 78.56,
      "last_close": 193.81,
      "atr": 5.616,
      "entry_zone": {
        "lower": 191.0,
        "upper": 198.3
      },
      "timeframe": "1d",
      "is_actionable": true,
      "analysis": [
        "RSI 58.2 - Neutral (trend: v)",
        "MACD Mild Bullish (spread: 0.9817, d_hist: -0.0295)",
        "OBV slope 138615425.3 - Bullish volume flow",
        "MA50 185.78 vs MA200 174.73 - Strong Bullish Trend (spread: 6.3%)",
        "BB Mild Bearish (upper half) - price middle<->upper (wide bands, width: 0.131)",
        "Volume 9,914,429 vs SMA20 171,708,446 - Weak Bearish (low volume) (ratio: 0.06x)",
        "Neutral Candlesticks 0.04 : bear_engulfing",
        "Near S/R level at $193.63"
      ]
    },
    {
      "ticker": "AMZN",
      "name": "AMZN",
      "signal": "BUY",
      "confidence": 65.98,
      "last_close": 210.45,
      "atr": 6.1371,
      "entry_zone": {
        "lower": 207.38,
        "upper": 215.36
      },
      "timeframe": "1d",
      "is_actionable": true,
      "analysis": [
        "RSI 42.2 - Neutral (trend: v)",
        "MACD Bullish Momentum (spread: 0.6568, d_hist: 0.4203)",
        "OBV slope 27363302.2 - Strong Bullish volume flow",
        "MA50 226.89 vs MA200 224.35 - Mild Bullish Trend (spread: 1.1%)",
        "BB Mild Bullish (lower half) - price lower<->middle (wide bands, width: 0.282)",
        "Volume 393,632 vs SMA20 62,615,021 - Weak Bearish (low volume) (ratio: 0.01x)",
        "Neutral Candlesticks 0.40 : bull_rising_sun",
        "Strong trend (ADX=73.8) - boosted confidence",
        "Near S/R level at $214.84"
      ]
    },
    {
      "ticker": "BABA",
      "name": "BABA",
      "signal": "BUY",
      "confidence": 77.35,
      "last_close": 148.08,
      "atr": 4.8003,
      "entry_zone": {
        "lower": 145.68,
        "upper": 151.92
      },
      "timeframe": "1d",
      "is_actionable": true,
      "analysis": [
        "RSI 33.7 - Neutral (trend: v)",
        "MACD Bearish Momentum (spread: -1.4002, d_hist: -0.1129)",
        "OBV slope 84763.6 - Strong Bullish volume flow",
        "MA50 158.72 vs MA200 145.03 - Mild Bullish Trend (spread: 9.4%)",
        "BB Bullish (near lower) - price lower<->middle (wide bands, width: 0.171)",
        "Volume 587,464 vs SMA20 8,712,813 - Weak Bearish (low volume) (ratio: 0.07x)",
        "Neutral Candlesticks 0.09 : ",
        "Strong trend (ADX=55.7) - boosted confidence",
        "Near S/R level at $148.64"
      ]
    },
    {
      "ticker": "V",
      "name": "V",
      "signal": "HOLD",
      "confidence": 61.83,
      "last_close": 315.58,
      "atr": 7.1521,
      "entry_zone": {
        "lower": 312.0,
        "upper": 321.3
      },
      "timeframe": "1d",
      "is_actionable": false,
      "analysis": [
        "RSI 42.7 - Neutral (trend: ^)",
        "MACD Neutral Bearish (spread: -0.6823, d_hist: 0.4434)",
        "OBV slope 5584050.4 - Strong Bullish volume flow",
        "MA50 334.26 vs MA200 343.31 - Bearish Trend (spread: -2.6%)",
        "BB Mild Bullish (lower half) - price lower<->middle (wide bands, width: 0.101)",
        "Volume 7,703 vs SMA20 8,275,809 - Weak Bullish (low volume) (ratio: 0.00x)",
        "Neutral Candlesticks 0.50 : bull_harami",
        "Near S/R level at $318.00"
      ]
    },
    {
      "ticker": "MA",
      "name": "MA",
      "signal": "HOLD",
      "confidence": 40.45,
      "last_close": 511.48,
      "atr": 12.7761,
      "entry_zone": {
        "lower": 505.09,
        "upper": 521.7
      },
      "timeframe": "1d",
      "is_actionable": false,
      "analysis": [
        "RSI 40.9 - Neutral (trend: ^)",
        "MACD Neutral Bearish (spread: -2.0810, d_hist: 0.6987)",
        "OBV slope 3145623.5 - Strong Bullish volume flow",
        "MA50 547.27 vs MA200 562.27 - Bearish Trend (spread: -2.7%)",
        "BB Mild Bullish (lower half) - price lower<->middle (wide bands, width: 0.136)",
        "Volume 4,943 vs SMA20 3,940,769 - Weak Bullish (low volume) (ratio: 0.00x)",
        "Neutral Candlesticks 0.31 : bull_rising_sun",
        "Near S/R level at $527.33"
      ]
    },
    {
      "ticker": "AMD",
      "name": "AMD",
      "signal": "BUY",
      "confidence": 70.89,
      "last_close": 207.33,
      "atr": 10.8904,
      "entry_zone": {
        "lower": 201.88,
        "upper": 216.04
      },
      "timeframe": "1d",
      "is_actionable": true,
      "analysis": [
        "RSI 45.5 - Neutral (trend: v)",
        "MACD Neutral Bearish (spread: -0.0920, d_hist: 0.3384)",
        "OBV slope 12007638.1 - Strong Bullish volume flow",
        "MA50 218.89 vs MA200 186.14 - Mild Bullish Trend (spread: 17.6%)",
        "BB Mild Bullish (lower half) - price lower<->middle (wide bands, width: 0.321)",
        "Volume 756,047 vs SMA20 41,363,101 - Weak Bearish (low volume) (ratio: 0.02x)",
        "Neutral Candlesticks 0.22 : bull_engulfing",
        "Strong trend (ADX=47.4) - boosted confidence"
      ]
    },
    {
      "ticker": "VOO",
      "name": "VOO",
      "signal": "BUY",
      "confidence": 86.05,
      "last_close": 637.28,
      "atr": 6.8203,
      "entry_zone": {
        "lower": 633.87,
        "upper": 642.74
      },
      "timeframe": "1d",
      "is_actionable": true,
      "analysis": [
        "RSI 54.8 - Neutral (trend: v)",
        "MACD Bullish Momentum (spread: 0.4500, d_hist: 0.2975)",
        "OBV slope 6325957.5 - Strong Bullish volume flow",
        "MA50 632.51 vs MA200 601.11 - Strong Bullish Trend (spread: 5.2%)",
        "BB Mild Bearish (upper half) - price middle<->upper (normal bands, width: 0.030)",
        "Volume 87,596 vs SMA20 8,879,195 - Weak Bearish (low volume) (ratio: 0.01x)",
        "Neutral Candlesticks 0.14 : bull_engulfing",
        "Near S/R level at $634.13"
      ]
    },
    {
      "ticker": "META",
      "name": "META",
      "signal": "HOLD",
      "confidence": 54.09,
      "last_close": 648.3,
      "atr": 18.7878,
      "entry_zone": {
        "lower": 638.91,
        "upper": 663.33
      },
      "timeframe": "1d",
      "is_actionable": false,
      "analysis": [
        "RSI 47.4 - Neutral (trend: v)",
        "MACD Neutral Bearish (spread: -2.1448, d_hist: 0.5995)",
        "OBV slope 6980129.5 - Strong Bullish volume flow",
        "MA50 656.51 vs MA200 691.20 - Strong Bearish Trend (spread: -5.0%)",
        "BB Mild Bullish (lower half) - price lower<->middle (wide bands, width: 0.169)",
        "Volume 525,953 vs SMA20 15,647,608 - Weak Bearish (low volume) (ratio: 0.03x)",
        "Neutral Candlesticks 0.16 : bull_harami",
        "Strong trend (ADX=40.6) - boosted confidence"
      ]
    }
  ]
}