{
  "report_date": "2026-03-02 04:27:43",
  "total_analyzed": 6,
  "summary": {
    "buy": 2,
    "sell": 0,
    "hold": 4
  },
  "signals": [
    {
      "ticker": "CRPU.SI",
      "name": "Sasseur Reit",
      "signal": "HOLD",
      "confidence": 34.83,
      "last_close": 0.68,
      "atr": 0.0072,
      "entry_zone": {
        "lower": 0.68,
        "upper": 0.69
      },
      "timeframe": "1d",
      "is_actionable": false,
      "analysis": [
        "RSI 44.1 - Neutral (trend: v)",
        "MACD Strong Bearish Crossover (spread: -0.0003, d_hist: -0.0003)",
        "OBV slope -613166.7 - Strong Bearish volume flow",
        "MA50 0.68 vs MA200 0.66 - Mild Bullish Trend (spread: 3.2%)",
        "BB Mild Bullish (lower half) - price lower<->middle (tight bands, width: 0.018)",
        "Volume 1,839,500 vs SMA20 1,295,010 - Bearish (above avg volume) (ratio: 1.42x)",
        "Neutral Candlesticks 0.41 : bull_marubozu",
        "Weak trend (ADX=15.8) - reduced confidence",
        "Near S/R level at $0.67"
      ]
    },
    {
      "ticker": "J69U.SI",
      "name": "Frasers Cpt Tr",
      "signal": "HOLD",
      "confidence": 41.5,
      "last_close": 2.27,
      "atr": 0.0268,
      "entry_zone": {
        "lower": 2.26,
        "upper": 2.29
      },
      "timeframe": "1d",
      "is_actionable": false,
      "analysis": [
        "RSI 50.3 - Neutral (trend: v)",
        "MACD Mild Bullish (spread: 0.0039, d_hist: -0.0020)",
        "OBV slope -643466.7 - Strong Bearish volume flow",
        "MA50 2.27 vs MA200 2.24 - Mild Bullish Trend (spread: 1.4%)",
        "BB Mild Bearish (upper half) - price middle<->upper (normal bands, width: 0.040)",
        "Volume 3,181,400 vs SMA20 5,276,835 - Weak Bearish (low volume) (ratio: 0.60x)",
        "Neutral Candlesticks 0.18 : bear_marubozu",
        "Near S/R level at $2.23"
      ]
    },
    {
      "ticker": "BUOU.SI",
      "name": "Frasers L&C Tr",
      "signal": "HOLD",
      "confidence": 29.69,
      "last_close": 0.99,
      "atr": 0.0169,
      "entry_zone": {
        "lower": 0.98,
        "upper": 1.0
      },
      "timeframe": "1d",
      "is_actionable": false,
      "analysis": [
        "RSI 37.3 - Neutral (trend: v)",
        "MACD Bearish Momentum (spread: -0.0015, d_hist: -0.0008)",
        "OBV slope -10871300.0 - Strong Bearish volume flow",
        "MA50 1.01 vs MA200 0.91 - Mild Bullish Trend (spread: 10.6%)",
        "BB Strong Bullish (<lower band) - price <lower (tight bands, width: 0.030)",
        "Volume 9,244,900 vs SMA20 9,099,327 - Mild Bearish (normal volume) (ratio: 1.02x)",
        "Neutral Candlesticks 0.23 : bear_marubozu",
        "Weak trend (ADX=14.1) - reduced confidence",
        "Near S/R level at $0.95"
      ]
    },
    {
      "ticker": "M44U.SI",
      "name": "Mapletree Log Tr",
      "signal": "BUY",
      "confidence": 67.82,
      "last_close": 1.27,
      "atr": 0.0179,
      "entry_zone": {
        "lower": 1.26,
        "upper": 1.28
      },
      "timeframe": "1d",
      "is_actionable": true,
      "analysis": [
        "RSI 33.6 - Neutral (trend: v)",
        "MACD Bearish Momentum (spread: -0.0031, d_hist: -0.0009)",
        "OBV slope -1625766.7 - Strong Bearish volume flow",
        "MA50 1.31 vs MA200 1.22 - Mild Bullish Trend (spread: 7.8%)",
        "BB Strong Bullish (<lower band) - price <lower (normal bands, width: 0.050)",
        "Volume 3,965,200 vs SMA20 11,965,640 - Weak Bearish (low volume) (ratio: 0.33x)",
        "Neutral Candlesticks 0.47 : bear_tweezer",
        "Strong trend (ADX=72.0) - boosted confidence",
        "Near S/R level at $1.26"
      ]
    },
    {
      "ticker": "ME8U.SI",
      "name": "Mapletree Ind Tr",
      "signal": "HOLD",
      "confidence": 52.88,
      "last_close": 2.02,
      "atr": 0.0195,
      "entry_zone": {
        "lower": 2.01,
        "upper": 2.04
      },
      "timeframe": "1d",
      "is_actionable": false,
      "analysis": [
        "RSI 38.1 - Neutral (trend: v)",
        "MACD Bearish Momentum (spread: -0.0015, d_hist: -0.0014)",
        "OBV slope -2558900.0 - Strong Bearish volume flow",
        "MA50 2.05 vs MA200 2.00 - Mild Bullish Trend (spread: 2.5%)",
        "BB Bullish (near lower) - price lower<->middle (tight bands, width: 0.028)",
        "Volume 2,670,200 vs SMA20 6,229,852 - Weak Bearish (low volume) (ratio: 0.43x)",
        "Neutral Candlesticks 0.16 : bear_marubozu",
        "Near S/R level at $2.00"
      ]
    },
    {
      "ticker": "JYEU.SI",
      "name": "Lendlease Reit",
      "signal": "BUY",
      "confidence": 67.28,
      "last_close": 0.57,
      "atr": 0.0132,
      "entry_zone": {
        "lower": 0.57,
        "upper": 0.59
      },
      "timeframe": "1d",
      "is_actionable": true,
      "analysis": [
        "RSI 24.7 - Bullish (trend: -)",
        "MACD Neutral Bearish (spread: -0.0060, d_hist: 0.0000)",
        "OBV slope -14786166.7 - Bearish volume flow",
        "MA50 0.62 vs MA200 0.57 - Mild Bullish Trend (spread: 8.0%)",
        "BB Bullish (near lower) - price lower<->middle (wide bands, width: 0.138)",
        "Volume 18,722,100 vs SMA20 20,360,500 - Neutral (normal volume) (ratio: 0.92x)",
        "Neutral Candlesticks 0.21 : bear_harami",
        "Near S/R level at $0.57"
      ]
    }
  ]
}