{
  "report_date": "2026-01-29 14:10:13",
  "total_analyzed": 11,
  "summary": {
    "buy": 7,
    "sell": 0,
    "hold": 4
  },
  "signals": [
    {
      "ticker": "AAPL",
      "name": "AAPL",
      "signal": "BUY",
      "confidence": 68.97,
      "last_close": 256.44,
      "atr": 5.1694,
      "entry_zone": {
        "lower": 253.86,
        "upper": 260.58
      },
      "timeframe": "1d",
      "is_actionable": true,
      "analysis": [
        "RSI 43.0 - Neutral (trend: v)",
        "MACD Strong Bullish Crossover (spread: 0.2705, d_hist: 0.3767)",
        "OBV slope 21443178.0 - Strong Bullish volume flow",
        "MA50 268.74 vs MA200 236.07 - Mild Bullish Trend (spread: 13.8%)",
        "BB Mild Bullish (lower half) - price lower<->middle (wide bands, width: 0.120)",
        "Volume 41,287,971 vs SMA20 46,487,706 - Mild Bearish (normal volume) (ratio: 0.89x)",
        "Neutral Candlesticks 0.12 : bull_engulfing",
        "Strong trend (ADX=48.8) - boosted confidence",
        "Near S/R level at $250.00"
      ]
    },
    {
      "ticker": "MSFT",
      "name": "MSFT",
      "signal": "HOLD",
      "confidence": 48.13,
      "last_close": 481.63,
      "atr": 9.8212,
      "entry_zone": {
        "lower": 476.72,
        "upper": 489.49
      },
      "timeframe": "1d",
      "is_actionable": false,
      "analysis": [
        "RSI 56.1 - Neutral (trend: ^)",
        "MACD Bullish Momentum (spread: 2.3257, d_hist: 0.9958)",
        "OBV slope 31793520.3 - Bullish volume flow",
        "MA50 479.19 vs MA200 485.50 - Mild Bearish Trend (spread: -1.3%)",
        "BB Mild Bearish (upper half) - price middle<->upper (wide bands, width: 0.105)",
        "Volume 36,875,403 vs SMA20 26,309,325 - Bullish (above avg volume) (ratio: 1.40x)",
        "Neutral Candlesticks 0.28 : bull_tweezer",
        "Near S/R level at $492.37"
      ]
    },
    {
      "ticker": "GOOGL",
      "name": "GOOGL",
      "signal": "HOLD",
      "confidence": 51.48,
      "last_close": 336.01,
      "atr": 7.4858,
      "entry_zone": {
        "lower": 332.27,
        "upper": 342.0
      },
      "timeframe": "1d",
      "is_actionable": false,
      "analysis": [
        "RSI 64.3 - Neutral (trend: ^)",
        "MACD Neutral Bearish (spread: -0.0637, d_hist: 0.1374)",
        "OBV slope 25037572.7 - Strong Bullish volume flow",
        "MA50 315.72 vs MA200 232.64 - Strong Bullish Trend (spread: 35.7%)",
        "BB Mild Bearish (upper half) - price middle<->upper (wide bands, width: 0.099)",
        "Volume 27,434,434 vs SMA20 29,226,774 - Mild Bullish (normal volume) (ratio: 0.94x)",
        "Neutral Candlesticks 0.12 : bull_rising_sun",
        "Near S/R level at $328.83"
      ]
    },
    {
      "ticker": "NVDA",
      "name": "NVDA",
      "signal": "BUY",
      "confidence": 86.64,
      "last_close": 191.52,
      "atr": 5.0204,
      "entry_zone": {
        "lower": 189.01,
        "upper": 195.54
      },
      "timeframe": "1d",
      "is_actionable": true,
      "analysis": [
        "RSI 58.6 - Neutral (trend: ^)",
        "MACD Bullish Momentum (spread: 0.4865, d_hist: 0.3046)",
        "OBV slope 55821528.3 - Strong Bullish volume flow",
        "MA50 183.68 vs MA200 166.95 - Strong Bullish Trend (spread: 10.0%)",
        "BB Bearish (near upper) - price middle<->upper (normal bands, width: 0.060)",
        "Volume 148,552,677 vs SMA20 157,938,123 - Mild Bullish (normal volume) (ratio: 0.94x)",
        "Neutral Candlesticks 0.24 : bull_rising_sun",
        "Near S/R level at $193.63"
      ]
    },
    {
      "ticker": "AMZN",
      "name": "AMZN",
      "signal": "HOLD",
      "confidence": 48.17,
      "last_close": 243.01,
      "atr": 5.4765,
      "entry_zone": {
        "lower": 240.27,
        "upper": 247.39
      },
      "timeframe": "1d",
      "is_actionable": false,
      "analysis": [
        "RSI 58.1 - Neutral (trend: v)",
        "MACD Bullish Momentum (spread: 0.1985, d_hist: 0.1958)",
        "OBV slope -11892990.3 - Strong Bearish volume flow",
        "MA50 232.27 vs MA200 221.21 - Bullish Trend (spread: 5.0%)",
        "BB Mild Bearish (upper half) - price middle<->upper (wide bands, width: 0.101)",
        "Volume 40,882,657 vs SMA20 39,726,996 - Mild Bearish (normal volume) (ratio: 1.03x)",
        "Neutral Candlesticks 0.69 : bear_harami",
        "Near S/R level at $236.53"
      ]
    },
    {
      "ticker": "BABA",
      "name": "BABA",
      "signal": "BUY",
      "confidence": 67.38,
      "last_close": 175.66,
      "atr": 6.0338,
      "entry_zone": {
        "lower": 172.64,
        "upper": 180.49
      },
      "timeframe": "1d",
      "is_actionable": true,
      "analysis": [
        "RSI 62.6 - Neutral (trend: ^)",
        "MACD Mild Bullish (spread: 1.4024, d_hist: -0.0707)",
        "OBV slope 2588872.3 - Strong Bullish volume flow",
        "MA50 158.00 vs MA200 140.91 - Strong Bullish Trend (spread: 12.1%)",
        "BB Mild Bearish (upper half) - price middle<->upper (wide bands, width: 0.255)",
        "Volume 9,001,486 vs SMA20 14,960,200 - Weak Bullish (low volume) (ratio: 0.60x)",
        "Neutral Candlesticks 0.39 : bull_engulfing",
        "Strong trend (ADX=40.9) - boosted confidence",
        "Near S/R level at $182.50"
      ]
    },
    {
      "ticker": "V",
      "name": "V",
      "signal": "BUY",
      "confidence": 75.04,
      "last_close": 326.98,
      "atr": 5.8919,
      "entry_zone": {
        "lower": 324.03,
        "upper": 331.69
      },
      "timeframe": "1d",
      "is_actionable": true,
      "analysis": [
        "RSI 37.6 - Bullish (trend: ^)",
        "MACD Neutral Bearish (spread: -1.4679, d_hist: 0.4114)",
        "OBV slope 3093435.7 - Strong Bullish volume flow",
        "MA50 337.36 vs MA200 344.99 - Bearish Trend (spread: -2.2%)",
        "BB Mild Bullish (lower half) - price lower<->middle (wide bands, width: 0.152)",
        "Volume 8,105,960 vs SMA20 7,804,566 - Mild Bullish (normal volume) (ratio: 1.04x)",
        "Neutral Candlesticks 0.12 : bear_harami",
        "Strong trend (ADX=59.4) - boosted confidence",
        "Near S/R level at $326.38"
      ]
    },
    {
      "ticker": "MA",
      "name": "MA",
      "signal": "BUY",
      "confidence": 81.16,
      "last_close": 521.37,
      "atr": 10.5086,
      "entry_zone": {
        "lower": 516.12,
        "upper": 529.78
      },
      "timeframe": "1d",
      "is_actionable": true,
      "analysis": [
        "RSI 30.8 - Bullish (trend: ^)",
        "MACD Neutral Bearish (spread: -4.0855, d_hist: 0.4623)",
        "OBV slope 2157309.0 - Strong Bullish volume flow",
        "MA50 552.45 vs MA200 562.98 - Bearish Trend (spread: -1.9%)",
        "BB Mild Bullish (lower half) - price lower<->middle (wide bands, width: 0.162)",
        "Volume 5,483,042 vs SMA20 4,016,058 - Bullish (above avg volume) (ratio: 1.37x)",
        "Neutral Candlesticks 0.57 : bear_tweezer",
        "Strong trend (ADX=61.7) - boosted confidence",
        "Near S/R level at $517.71"
      ]
    },
    {
      "ticker": "AMD",
      "name": "AMD",
      "signal": "BUY",
      "confidence": 68.16,
      "last_close": 252.74,
      "atr": 10.0638,
      "entry_zone": {
        "lower": 247.71,
        "upper": 260.79
      },
      "timeframe": "1d",
      "is_actionable": true,
      "analysis": [
        "RSI 67.8 - Neutral (trend: ^)",
        "MACD Mild Bullish (spread: 3.6647, d_hist: -0.5566)",
        "OBV slope 7360108.0 - Bullish volume flow",
        "MA50 221.22 vs MA200 174.30 - Strong Bullish Trend (spread: 26.9%)",
        "BB Mild Bearish (upper half) - price middle<->upper (wide bands, width: 0.323)",
        "Volume 27,061,187 vs SMA20 36,096,677 - Mild Bullish (normal volume) (ratio: 0.75x)",
        "Neutral Candlesticks 0.28 : bear_dark_cloud"
      ]
    },
    {
      "ticker": "VOO",
      "name": "VOO",
      "signal": "BUY",
      "confidence": 88.8,
      "last_close": 639.6,
      "atr": 5.443,
      "entry_zone": {
        "lower": 636.88,
        "upper": 643.95
      },
      "timeframe": "1d",
      "is_actionable": true,
      "analysis": [
        "RSI 58.6 - Neutral (trend: v)",
        "MACD Strong Bullish Crossover (spread: 0.1768, d_hist: 0.2089)",
        "OBV slope 2592755.7 - Bullish volume flow",
        "MA50 627.95 vs MA200 588.06 - Strong Bullish Trend (spread: 6.8%)",
        "BB Mild Bearish (upper half) - price middle<->upper (tight bands, width: 0.028)",
        "Volume 5,568,673 vs SMA20 8,345,022 - Weak Bearish (low volume) (ratio: 0.67x)",
        "Neutral Candlesticks 0.00 : ",
        "Near S/R level at $634.13"
      ]
    },
    {
      "ticker": "META",
      "name": "META",
      "signal": "HOLD",
      "confidence": 44.62,
      "last_close": 668.73,
      "atr": 16.9229,
      "entry_zone": {
        "lower": 660.27,
        "upper": 682.27
      },
      "timeframe": "1d",
      "is_actionable": false,
      "analysis": [
        "RSI 58.6 - Neutral (trend: v)",
        "MACD Bullish Momentum (spread: 4.9642, d_hist: 0.4931)",
        "OBV slope 1305042.7 - Bullish volume flow",
        "MA50 643.02 vs MA200 679.51 - Mild Bearish Trend (spread: -5.4%)",
        "BB Mild Bearish (upper half) - price middle<->upper (wide bands, width: 0.131)",
        "Volume 25,709,600 vs SMA20 14,909,021 - Bearish (above avg volume) (ratio: 1.72x)",
        "Neutral Candlesticks 0.60 : bull_rising_sun",
        "Near S/R level at $691.20"
      ]
    }
  ]
}